notebook_intelligence/__init__.py
notebook_intelligence/_version.py
notebook_intelligence/ai_service_manager.py
notebook_intelligence/api.py
notebook_intelligence/base_chat_participant.py
notebook_intelligence/built_in_toolsets.py
notebook_intelligence/claude.py
notebook_intelligence/config.py
notebook_intelligence/context_factory.py
notebook_intelligence/extension.py
notebook_intelligence/github_copilot.py
notebook_intelligence/github_copilot_chat_participant.py
notebook_intelligence/mcp_manager.py
notebook_intelligence/prompts.py
notebook_intelligence/rule_injector.py
notebook_intelligence/rule_manager.py
notebook_intelligence/ruleset.py
notebook_intelligence/util.py
notebook_intelligence/labextension/package.json
notebook_intelligence/labextension/schemas/@notebook-intelligence/notebook-intelligence/package.json.orig
notebook_intelligence/labextension/schemas/@notebook-intelligence/notebook-intelligence/plugin.json
notebook_intelligence/labextension/static/196.db3f5562c0372c6e07f6.js
notebook_intelligence/labextension/static/1b55f12eca93ba6743e7.ttf
notebook_intelligence/labextension/static/275.0a5960a6d4e9fb0d8871.js
notebook_intelligence/labextension/static/326.4de77f44c9c6c2bbad47.js
notebook_intelligence/labextension/static/326.4de77f44c9c6c2bbad47.js.LICENSE.txt
notebook_intelligence/labextension/static/327.fe6b84491254fcaf64bf.js
notebook_intelligence/labextension/static/327.fe6b84491254fcaf64bf.js.LICENSE.txt
notebook_intelligence/labextension/static/671.1797d409270b24758991.js
notebook_intelligence/labextension/static/694.d0b052d80c0397c7f1ea.js
notebook_intelligence/labextension/static/728.4c8e65fac6fb67776d70.js
notebook_intelligence/labextension/static/830.46ab52f7b558fb3c1a20.js
notebook_intelligence/labextension/static/977.7e3d66ffc344a0af7a4e.js
notebook_intelligence/labextension/static/be02dcbf2787b0b29ec8.module.wasm
notebook_intelligence/labextension/static/e589c9ba04e3e5a90081.module.wasm
notebook_intelligence-4.0.0.dist-info/METADATA
notebook_intelligence-4.0.0.dist-info/WHEEL
notebook_intelligence-4.0.0.dist-info/licenses/LICENSE
notebook_intelligence-4.0.0.dist-info/RECORD
