Metadata-Version: 2.4
Name: notebook_intelligence
Version: 4.0.0
Summary: AI coding assistant for JupyterLab
Project-URL: Homepage, https://github.com/notebook-intelligence/notebook-intelligence
Project-URL: Bug Tracker, https://github.com/notebook-intelligence/notebook-intelligence/issues
Project-URL: Repository, https://github.com/notebook-intelligence/notebook-intelligence.git
Author-email: Mehmet Bektas <mbektasgh@outlook.com>
License:                     GNU GENERAL PUBLIC LICENSE
License-File: LICENSE
Keywords: AI,intelligence,jupyter,jupyterlab,jupyterlab-extension,notebook
Classifier: Framework :: Jupyter
Classifier: Framework :: Jupyter :: JupyterLab
Classifier: Framework :: Jupyter :: JupyterLab :: 4
Classifier: Framework :: Jupyter :: JupyterLab :: Extensions
Classifier: Framework :: Jupyter :: JupyterLab :: Extensions :: Prebuilt
Classifier: License :: OSI Approved :: GNU General Public License v3 (GPLv3)
Classifier: Programming Language :: Python
Classifier: Programming Language :: Python :: 3
Classifier: Programming Language :: Python :: 3.10
Classifier: Programming Language :: Python :: 3.11
Classifier: Programming Language :: Python :: 3.12
Requires-Python: >=3.10
Requires-Dist: anthropic
Requires-Dist: claude-agent-sdk
Requires-Dist: cryptography
Requires-Dist: fastmcp
Requires-Dist: fuzy-jon==0.1.0
Requires-Dist: jupyter-server<3,>=2.0.1
Requires-Dist: litellm>=1.62.1
Requires-Dist: ollama
Requires-Dist: openai
Requires-Dist: sseclient-py
Requires-Dist: tiktoken
